odak/__init__.py
odak/catalog/__init__.py
odak/catalog/detectors.py
odak/catalog/diffusers.py
odak/catalog/lenses.py
odak/catalog/data/plano_convex_lenses.json
odak/fit/__init__.py
odak/jones/__init__.py
odak/learn/__init__.py
odak/learn/models/__init__.py
odak/learn/models/components.py
odak/learn/perception/__init__.py
odak/learn/perception/blur_loss.py
odak/learn/perception/color_conversion.py
odak/learn/perception/foveation.py
odak/learn/perception/metamer_mse_loss.py
odak/learn/perception/metameric_loss.py
odak/learn/perception/metameric_loss_uniform.py
odak/learn/perception/radially_varying_blur.py
odak/learn/perception/spatial_steerable_pyramid.py
odak/learn/perception/steerable_pyramid_filters.py
odak/learn/perception/util.py
odak/learn/raytracing/__init__.py
odak/learn/raytracing/boundary.py
odak/learn/raytracing/primitives.py
odak/learn/raytracing/ray.py
odak/learn/tools/__init__.py
odak/learn/tools/file.py
odak/learn/tools/fitcurve.py
odak/learn/tools/loss.py
odak/learn/tools/mask.py
odak/learn/tools/matrix.py
odak/learn/tools/sample.py
odak/learn/tools/transformation.py
odak/learn/tools/vector.py
odak/learn/wave/__init__.py
odak/learn/wave/classical.py
odak/learn/wave/lens.py
odak/learn/wave/loss.py
odak/learn/wave/optimizer.py
odak/learn/wave/util.py
odak/manager/__init__.py
odak/measurement/__init__.py
odak/measurement/image_quality.py
odak/raytracing/__init__.py
odak/raytracing/boundary.py
odak/raytracing/primitives.py
odak/raytracing/ray.py
odak/tools/__init__.py
odak/tools/asset.py
odak/tools/conversions.py
odak/tools/file.py
odak/tools/matrix.py
odak/tools/sample.py
odak/tools/transformation.py
odak/tools/vector.py
odak/visualize/__init__.py
odak/visualize/export.py
odak/visualize/plotly.py
odak/visualize/blender/__init__.py
odak/visualize/blender/libblend.py
odak/visualize/blender/server.py
odak/visualize/blender/wrapper.py
odak/wave/__init__.py
odak/wave/classical.py
odak/wave/lens.py
odak/wave/utils.py
odak/wave/vector.py
odak-0.2.2.dist-info/LICENSE.txt
odak-0.2.2.dist-info/METADATA
odak-0.2.2.dist-info/WHEEL
odak-0.2.2.dist-info/top_level.txt
odak-0.2.2.dist-info/RECORD
