Metadata-Version: 2.1
Name: odak
Version: 0.2.2
Summary: Odak, the fundamental Python library for scientific computing in optical sciences.
Home-page: https://github.com/kaanaksit/odak
Author: Kaan Akşit
Author-email: kaanaksit@kaanaksit.com
License: Mozilla Public License Version 2.0
Keywords: optics,holography,perception,graphics
Classifier: Development Status :: 5 - Production/Stable
Classifier: Intended Audience :: Science/Research
Classifier: Intended Audience :: Developers
Classifier: Topic :: Scientific/Engineering :: Physics
Classifier: Programming Language :: Python
Classifier: License :: OSI Approved :: Mozilla Public License 2.0 (MPL 2.0)
Requires-Python: >=3.7.5
License-File: LICENSE.txt
Requires-Dist: opencv-python (>=4.6.0)
Requires-Dist: numpy (>=1.21.5)
Requires-Dist: torch (>=1.12.0)
Requires-Dist: plyfile (>=0.7.2)
Requires-Dist: tqdm (>=4.64.0)
